batux_lib_test/__init__.py
batux_lib_test/lib_stuff.pyx
batux_lib_test/py.typed
batux_lib_test-0.1.4.dist-info/METADATA
batux_lib_test-0.1.4.dist-info/WHEEL
batux_lib_test-0.1.4.dist-info/RECORD
