Metadata-Version: 2.4
Name: batux-lib-test
Version: 0.1.4
Summary: Add your description here
Author-email: Batuhan Avcı <batuhanavcix@gmail.com>
Requires-Python: >=3.12
Requires-Dist: cython>=3.0.11
Provides-Extra: build
Requires-Dist: cython; extra == 'build'
